Workbook

Sheet Leasing
A1: LEASE-DEMO-001 — Leasing (เช่ารถระยะยาว · net/ROU)
A3: PRINCIPAL / ROU (NPV) | B3: 800000 | D3: ROU LIFE (เดือน) | E3: 36
A4: RATE / YEAR (%) | B4: 4 | D4: PAYMENT START DATE | E4: 46295 | G4: INSTALLMENT = PMT (แก้เป็นค่าระบบได้) | H4: =ROUND(-PMT($B$4/100/12,$B$5,$B$3),2)
A5: TERM (MONTHS) | B5: 36 | D5: UPFRONT (จ่ายล่วงหน้าวันแรก) | E5: 0 | G5: ดอกเบี้ยรวมทั้งสัญญา | H5: =SUM(D10:D45)
A9: # | B9: PAYMENT DATE | C9: INSTALLMENT | D9: INTEREST | E9: PRINCIPAL (ตัดต้น) | F9: LIABILITY BALANCE | G9: DEPRECIATION | H9: ROU BALANCE
A10: 1 | B10: =EOMONTH($E$5,1) | C10: =IF(1=$B$5,F9+D10,$H$4) | D10: =ROUND($B$3*$B$4/100*J10/365,2) | E10: =C10-D10 | F10: =$B$3-E10 | G10: =ROUND(($B$3+$E$5)/$E$3,2) | H10: =($B$3+$E$5)-G10 | I10: =B10-$E$5 | J10: =B10-$E$5
A11: 2 | B11: =EOMONTH($E$5,2) | C11: =IF(2=$B$5,F10+D11,$H$4) | D11: =ROUND(F10*$B$4/100*J11/365,2) | E11: =C11-D11 | F11: =F10-E11 | G11: =ROUND(($B$3+$E$5)/$E$3,2) | H11: =H10-G11 | I11: =B11-B10 | J11: =B11-B10
A12: 3 | B12: =EOMONTH($E$5,3) | C12: =IF(3=$B$5,F11+D12,$H$4) | D12: =ROUND(F11*$B$4/100*J12/365,2) | E12: =C12-D12 | F12: =F11-E12 | G12: =ROUND(($B$3+$E$5)/$E$3,2) | H12: =H11-G12 | I12: =B12-B11 | J12: =B12-B11
A13: 4 | B13: =EOMONTH($E$5,4) | C13: =IF(4=$B$5,F12+D13,$H$4) | D13: =ROUND(F12*$B$4/100*J13/365,2) | E13: =C13-D13 | F13: =F12-E13 | G13: =ROUND(($B$3+$E$5)/$E$3,2) | H13: =H12-G13 | I13: =B13-B12 | J13: =B13-B12
A14: 5 | B14: =EOMONTH($E$5,5) | C14: =IF(5=$B$5,F13+D14,$H$4) | D14: =ROUND(F13*$B$4/100*J14/365,2) | E14: =C14-D14 | F14: =F13-E14 | G14: =ROUND(($B$3+$E$5)/$E$3,2) | H14: =H13-G14 | I14: =B14-B13 | J14: =B14-B13
A15: 6 | B15: =EOMONTH($E$5,6) | C15: =IF(6=$B$5,F14+D15,$H$4) | D15: =ROUND(F14*$B$4/100*J15/365,2) | E15: =C15-D15 | F15: =F14-E15 | G15: =ROUND(($B$3+$E$5)/$E$3,2) | H15: =H14-G15 | I15: =B15-B14 | J15: =B15-B14
A16: 7 | B16: =EOMONTH($E$5,7) | C16: =IF(7=$B$5,F15+D16,$H$4) | D16: =ROUND(F15*$B$4/100*J16/365,2) | E16: =C16-D16 | F16: =F15-E16 | G16: =ROUND(($B$3+$E$5)/$E$3,2) | H16: =H15-G16 | I16: =B16-B15 | J16: =B16-B15
A17: 8 | B17: =EOMONTH($E$5,8) | C17: =IF(8=$B$5,F16+D17,$H$4) | D17: =ROUND(F16*$B$4/100*J17/365,2) | E17: =C17-D17 | F17: =F16-E17 | G17: =ROUND(($B$3+$E$5)/$E$3,2) | H17: =H16-G17 | I17: =B17-B16 | J17: =B17-B16
A18: 9 | B18: =EOMONTH($E$5,9) | C18: =IF(9=$B$5,F17+D18,$H$4) | D18: =ROUND(F17*$B$4/100*J18/365,2) | E18: =C18-D18 | F18: =F17-E18 | G18: =ROUND(($B$3+$E$5)/$E$3,2) | H18: =H17-G18 | I18: =B18-B17 | J18: =B18-B17
A19: 10 | B19: =EOMONTH($E$5,10) | C19: =IF(10=$B$5,F18+D19,$H$4) | D19: =ROUND(F18*$B$4/100*J19/365,2) | E19: =C19-D19 | F19: =F18-E19 | G19: =ROUND(($B$3+$E$5)/$E$3,2) | H19: =H18-G19 | I19: =B19-B18 | J19: =B19-B18
A20: 11 | B20: =EOMONTH($E$5,11) | C20: =IF(11=$B$5,F19+D20,$H$4) | D20: =ROUND(F19*$B$4/100*J20/365,2) | E20: =C20-D20 | F20: =F19-E20 | G20: =ROUND(($B$3+$E$5)/$E$3,2) | H20: =H19-G20 | I20: =B20-B19 | J20: =B20-B19
A21: 12 | B21: =EOMONTH($E$5,12) | C21: =IF(12=$B$5,F20+D21,$H$4) | D21: =ROUND(F20*$B$4/100*J21/365,2) | E21: =C21-D21 | F21: =F20-E21 | G21: =ROUND(($B$3+$E$5)/$E$3,2) | H21: =H20-G21 | I21: =B21-B20 | J21: =B21-B20
A22: 13 | B22: =EOMONTH($E$5,13) | C22: =IF(13=$B$5,F21+D22,$H$4) | D22: =ROUND(F21*$B$4/100*J22/365,2) | E22: =C22-D22 | F22: =F21-E22 | G22: =ROUND(($B$3+$E$5)/$E$3,2) | H22: =H21-G22 | I22: =B22-B21 | J22: =B22-B21
A23: 14 | B23: =EOMONTH($E$5,14) | C23: =IF(14=$B$5,F22+D23,$H$4) | D23: =ROUND(F22*$B$4/100*J23/365,2) | E23: =C23-D23 | F23: =F22-E23 | G23: =ROUND(($B$3+$E$5)/$E$3,2) | H23: =H22-G23 | I23: =B23-B22 | J23: =B23-B22
A24: 15 | B24: =EOMONTH($E$5,15) | C24: =IF(15=$B$5,F23+D24,$H$4) | D24: =ROUND(F23*$B$4/100*J24/365,2) | E24: =C24-D24 | F24: =F23-E24 | G24: =ROUND(($B$3+$E$5)/$E$3,2) | H24: =H23-G24 | I24: =B24-B23 | J24: =B24-B23
A25: 16 | B25: =EOMONTH($E$5,16) | C25: =IF(16=$B$5,F24+D25,$H$4) | D25: =ROUND(F24*$B$4/100*J25/365,2) | E25: =C25-D25 | F25: =F24-E25 | G25: =ROUND(($B$3+$E$5)/$E$3,2) | H25: =H24-G25 | I25: =B25-B24 | J25: =B25-B24
A26: 17 | B26: =EOMONTH($E$5,17) | C26: =IF(17=$B$5,F25+D26,$H$4) | D26: =ROUND(F25*$B$4/100*J26/365,2) | E26: =C26-D26 | F26: =F25-E26 | G26: =ROUND(($B$3+$E$5)/$E$3,2) | H26: =H25-G26 | I26: =B26-B25 | J26: =B26-B25
A27: 18 | B27: =EOMONTH($E$5,18) | C27: =IF(18=$B$5,F26+D27,$H$4) | D27: =ROUND(F26*$B$4/100*J27/365,2) | E27: =C27-D27 | F27: =F26-E27 | G27: =ROUND(($B$3+$E$5)/$E$3,2) | H27: =H26-G27 | I27: =B27-B26 | J27: =B27-B26
A28: 19 | B28: =EOMONTH($E$5,19) | C28: =IF(19=$B$5,F27+D28,$H$4) | D28: =ROUND(F27*$B$4/100*J28/365,2) | E28: =C28-D28 | F28: =F27-E28 | G28: =ROUND(($B$3+$E$5)/$E$3,2) | H28: =H27-G28 | I28: =B28-B27 | J28: =B28-B27
A29: 20 | B29: =EOMONTH($E$5,20) | C29: =IF(20=$B$5,F28+D29,$H$4) | D29: =ROUND(F28*$B$4/100*J29/365,2) | E29: =C29-D29 | F29: =F28-E29 | G29: =ROUND(($B$3+$E$5)/$E$3,2) | H29: =H28-G29 | I29: =B29-B28 | J29: =B29-B28
A30: 21 | B30: =EOMONTH($E$5,21) | C30: =IF(21=$B$5,F29+D30,$H$4) | D30: =ROUND(F29*$B$4/100*J30/365,2) | E30: =C30-D30 | F30: =F29-E30 | G30: =ROUND(($B$3+$E$5)/$E$3,2) | H30: =H29-G30 | I30: =B30-B29 | J30: =B30-B29
A31: 22 | B31: =EOMONTH($E$5,22) | C31: =IF(22=$B$5,F30+D31,$H$4) | D31: =ROUND(F30*$B$4/100*J31/365,2) | E31: =C31-D31 | F31: =F30-E31 | G31: =ROUND(($B$3+$E$5)/$E$3,2) | H31: =H30-G31 | I31: =B31-B30 | J31: =B31-B30
A32: 23 | B32: =EOMONTH($E$5,23) | C32: =IF(23=$B$5,F31+D32,$H$4) | D32: =ROUND(F31*$B$4/100*J32/365,2) | E32: =C32-D32 | F32: =F31-E32 | G32: =ROUND(($B$3+$E$5)/$E$3,2) | H32: =H31-G32 | I32: =B32-B31 | J32: =B32-B31
A33: 24 | B33: =EOMONTH($E$5,24) | C33: =IF(24=$B$5,F32+D33,$H$4) | D33: =ROUND(F32*$B$4/100*J33/365,2) | E33: =C33-D33 | F33: =F32-E33 | G33: =ROUND(($B$3+$E$5)/$E$3,2) | H33: =H32-G33 | I33: =B33-B32 | J33: =B33-B32
A34: 25 | B34: =EOMONTH($E$5,25) | C34: =IF(25=$B$5,F33+D34,$H$4) | D34: =ROUND(F33*$B$4/100*J34/365,2) | E34: =C34-D34 | F34: =F33-E34 | G34: =ROUND(($B$3+$E$5)/$E$3,2) | H34: =H33-G34 | I34: =B34-B33 | J34: =B34-B33
A35: 26 | B35: =EOMONTH($E$5,26) | C35: =IF(26=$B$5,F34+D35,$H$4) | D35: =ROUND(F34*$B$4/100*J35/365,2) | E35: =C35-D35 | F35: =F34-E35 | G35: =ROUND(($B$3+$E$5)/$E$3,2) | H35: =H34-G35 | I35: =B35-B34 | J35: =B35-B34
A36: 27 | B36: =EOMONTH($E$5,27) | C36: =IF(27=$B$5,F35+D36,$H$4) | D36: =ROUND(F35*$B$4/100*J36/365,2) | E36: =C36-D36 | F36: =F35-E36 | G36: =ROUND(($B$3+$E$5)/$E$3,2) | H36: =H35-G36 | I36: =B36-B35 | J36: =B36-B35
A37: 28 | B37: =EOMONTH($E$5,28) | C37: =IF(28=$B$5,F36+D37,$H$4) | D37: =ROUND(F36*$B$4/100*J37/365,2) | E37: =C37-D37 | F37: =F36-E37 | G37: =ROUND(($B$3+$E$5)/$E$3,2) | H37: =H36-G37 | I37: =B37-B36 | J37: =B37-B36
A38: 29 | B38: =EOMONTH($E$5,29) | C38: =IF(29=$B$5,F37+D38,$H$4) | D38: =ROUND(F37*$B$4/100*J38/365,2) | E38: =C38-D38 | F38: =F37-E38 | G38: =ROUND(($B$3+$E$5)/$E$3,2) | H38: =H37-G38 | I38: =B38-B37 | J38: =B38-B37
A39: 30 | B39: =EOMONTH($E$5,30) | C39: =IF(30=$B$5,F38+D39,$H$4) | D39: =ROUND(F38*$B$4/100*J39/365,2) | E39: =C39-D39 | F39: =F38-E39 | G39: =ROUND(($B$3+$E$5)/$E$3,2) | H39: =H38-G39 | I39: =B39-B38 | J39: =B39-B38
A40: 31 | B40: =EOMONTH($E$5,31) | C40: =IF(31=$B$5,F39+D40,$H$4) | D40: =ROUND(F39*$B$4/100*J40/365,2) | E40: =C40-D40 | F40: =F39-E40 | G40: =ROUND(($B$3+$E$5)/$E$3,2) | H40: =H39-G40 | I40: =B40-B39 | J40: =B40-B39
A41: 32 | B41: =EOMONTH($E$5,32) | C41: =IF(32=$B$5,F40+D41,$H$4) | D41: =ROUND(F40*$B$4/100*J41/365,2) | E41: =C41-D41 | F41: =F40-E41 | G41: =ROUND(($B$3+$E$5)/$E$3,2) | H41: =H40-G41 | I41: =B41-B40 | J41: =B41-B40
A42: 33 | B42: =EOMONTH($E$5,33) | C42: =IF(33=$B$5,F41+D42,$H$4) | D42: =ROUND(F41*$B$4/100*J42/365,2) | E42: =C42-D42 | F42: =F41-E42 | G42: =ROUND(($B$3+$E$5)/$E$3,2) | H42: =H41-G42 | I42: =B42-B41 | J42: =B42-B41
A43: 34 | B43: =EOMONTH($E$5,34) | C43: =IF(34=$B$5,F42+D43,$H$4) | D43: =ROUND(F42*$B$4/100*J43/365,2) | E43: =C43-D43 | F43: =F42-E43 | G43: =ROUND(($B$3+$E$5)/$E$3,2) | H43: =H42-G43 | I43: =B43-B42 | J43: =B43-B42
A44: 35 | B44: =EOMONTH($E$5,35) | C44: =IF(35=$B$5,F43+D44,$H$4) | D44: =ROUND(F43*$B$4/100*J44/365,2) | E44: =C44-D44 | F44: =F43-E44 | G44: =ROUND(($B$3+$E$5)/$E$3,2) | H44: =H43-G44 | I44: =B44-B43 | J44: =B44-B43
A45: 36 | B45: =EOMONTH($E$5,36) | C45: =IF(36=$B$5,F44+D45,$H$4) | D45: =ROUND(F44*$B$4/100*J45/365,2) | E45: =C45-D45 | F45: =F44-E45 | G45: =ROUND(($B$3+$E$5)/$E$3,2) | H45: =H44-G45 | I45: =B45-B44 | J45: =B45-B44

Sheet Leasing Maturity
A1: LEASE-DEMO-001 — Maturity Profile
A3: GL Classification — Aging | D3: ที่มา / วิธีคิด (อ้างอิงแท็บ schedule)
A4: Current Portion (≤ 12 เดือน) | C4: =SUM(Leasing!E10:E21) | D4: รวม "เงินต้นตัดต่องวด" (คอลัมน์ PRINCIPAL (ตัดต้น) — ตัวเลขสีเขียว) ของงวดที่ 1–12
A5: Non-current (> 12 เดือน) | C5: =SUM(Leasing!E22:E45) | D5: รวม "เงินต้นตัดต่องวด" (PRINCIPAL สีเขียว) ของงวดที่ 13–36 (หรือ Total ลบ Current)
A6: Total Principal | C6: =Leasing!$B$3 | D6: เงินต้นตั้งต้น — ช่อง PRINCIPAL / ROU (มุมบนซ้ายของแท็บ schedule)
A8: ภาระผูกพันในอนาคต (เงินต้น + ดอกเบี้ย ยังไม่คิดลด) | D8: ที่มา / วิธีคิด
A9: ภายใน 1 ปี | C9: =SUMPRODUCT((Leasing!A10:A45<=12)*(Leasing!E10:E45+Leasing!D10:D45)) | D9: รวม "เงินต้นตัดต่องวด (PRINCIPAL สีเขียว)" + "ดอกเบี้ย (INTEREST สีส้ม)" ของงวดที่ 1–12 (เงินสดที่จะจ่ายใน 1 ปีข้างหน้า)
A10: 1 - 5 ปี | C10: =SUMPRODUCT((Leasing!A10:A45>12)*(Leasing!A10:A45<=60)*(Leasing!E10:E45+Leasing!D10:D45)) | D10: รวม PRINCIPAL (สีเขียว) + INTEREST (สีส้ม) ของงวดที่ 13–60
A11: มากกว่า 5 ปี | C11: =SUMPRODUCT((Leasing!A10:A45>60)*(Leasing!E10:E45+Leasing!D10:D45)) | D11: รวม PRINCIPAL + INTEREST ของงวดที่เกิน 60 เดือน — สัญญามี 36 งวด จึงไม่มี = 0
A12: Total Future Cash Flow | C12: =Leasing!$B$3+Leasing!$H$5 | D12: ช่อง PRINCIPAL บวก "ดอกเบี้ยรวมทั้งสัญญา" (INTEREST สีส้มรวมทุกงวด) (กระแสเงินสดอนาคตทั้งหมด ยังไม่คิดลด)
A14: Lease Classification: Finance (net/ROU · TFRS16)

Sheet Lease Other
A1: LSO-DEMO-001 — Lease Other (เช่าอาคาร · net/ROU)
A3: PRINCIPAL / ROU (NPV) | B3: 900000 | D3: ROU LIFE (เดือน) | E3: 60
A4: RATE / YEAR (%) | B4: 3.5 | D4: PAYMENT START DATE | E4: 46295 | G4: INSTALLMENT = PMT (แก้เป็นค่าระบบได้) | H4: =ROUND(-PMT($B$4/100/12,$B$5,$B$3),2)
A5: TERM (MONTHS) | B5: 60 | D5: UPFRONT (จ่ายล่วงหน้าวันแรก) | E5: 50000 | G5: ดอกเบี้ยรวมทั้งสัญญา | H5: =SUM(D10:D69)
A9: # | B9: PAYMENT DATE | C9: INSTALLMENT | D9: INTEREST | E9: PRINCIPAL (ตัดต้น) | F9: LIABILITY BALANCE | G9: DEPRECIATION | H9: ROU BALANCE
A10: 1 | B10: =EOMONTH($E$5,1) | C10: =IF(1=$B$5,F9+D10,$H$4) | D10: =ROUND($B$3*$B$4/100*J10/365,2) | E10: =C10-D10 | F10: =$B$3-E10 | G10: =ROUND(($B$3+$E$5)/$E$3,2) | H10: =($B$3+$E$5)-G10 | I10: =B10-$E$5 | J10: =B10-$E$5
A11: 2 | B11: =EOMONTH($E$5,2) | C11: =IF(2=$B$5,F10+D11,$H$4) | D11: =ROUND(F10*$B$4/100*J11/365,2) | E11: =C11-D11 | F11: =F10-E11 | G11: =ROUND(($B$3+$E$5)/$E$3,2) | H11: =H10-G11 | I11: =B11-B10 | J11: =B11-B10
A12: 3 | B12: =EOMONTH($E$5,3) | C12: =IF(3=$B$5,F11+D12,$H$4) | D12: =ROUND(F11*$B$4/100*J12/365,2) | E12: =C12-D12 | F12: =F11-E12 | G12: =ROUND(($B$3+$E$5)/$E$3,2) | H12: =H11-G12 | I12: =B12-B11 | J12: =B12-B11
A13: 4 | B13: =EOMONTH($E$5,4) | C13: =IF(4=$B$5,F12+D13,$H$4) | D13: =ROUND(F12*$B$4/100*J13/365,2) | E13: =C13-D13 | F13: =F12-E13 | G13: =ROUND(($B$3+$E$5)/$E$3,2) | H13: =H12-G13 | I13: =B13-B12 | J13: =B13-B12
A14: 5 | B14: =EOMONTH($E$5,5) | C14: =IF(5=$B$5,F13+D14,$H$4) | D14: =ROUND(F13*$B$4/100*J14/365,2) | E14: =C14-D14 | F14: =F13-E14 | G14: =ROUND(($B$3+$E$5)/$E$3,2) | H14: =H13-G14 | I14: =B14-B13 | J14: =B14-B13
A15: 6 | B15: =EOMONTH($E$5,6) | C15: =IF(6=$B$5,F14+D15,$H$4) | D15: =ROUND(F14*$B$4/100*J15/365,2) | E15: =C15-D15 | F15: =F14-E15 | G15: =ROUND(($B$3+$E$5)/$E$3,2) | H15: =H14-G15 | I15: =B15-B14 | J15: =B15-B14
A16: 7 | B16: =EOMONTH($E$5,7) | C16: =IF(7=$B$5,F15+D16,$H$4) | D16: =ROUND(F15*$B$4/100*J16/365,2) | E16: =C16-D16 | F16: =F15-E16 | G16: =ROUND(($B$3+$E$5)/$E$3,2) | H16: =H15-G16 | I16: =B16-B15 | J16: =B16-B15
A17: 8 | B17: =EOMONTH($E$5,8) | C17: =IF(8=$B$5,F16+D17,$H$4) | D17: =ROUND(F16*$B$4/100*J17/365,2) | E17: =C17-D17 | F17: =F16-E17 | G17: =ROUND(($B$3+$E$5)/$E$3,2) | H17: =H16-G17 | I17: =B17-B16 | J17: =B17-B16
A18: 9 | B18: =EOMONTH($E$5,9) | C18: =IF(9=$B$5,F17+D18,$H$4) | D18: =ROUND(F17*$B$4/100*J18/365,2) | E18: =C18-D18 | F18: =F17-E18 | G18: =ROUND(($B$3+$E$5)/$E$3,2) | H18: =H17-G18 | I18: =B18-B17 | J18: =B18-B17
A19: 10 | B19: =EOMONTH($E$5,10) | C19: =IF(10=$B$5,F18+D19,$H$4) | D19: =ROUND(F18*$B$4/100*J19/365,2) | E19: =C19-D19 | F19: =F18-E19 | G19: =ROUND(($B$3+$E$5)/$E$3,2) | H19: =H18-G19 | I19: =B19-B18 | J19: =B19-B18
A20: 11 | B20: =EOMONTH($E$5,11) | C20: =IF(11=$B$5,F19+D20,$H$4) | D20: =ROUND(F19*$B$4/100*J20/365,2) | E20: =C20-D20 | F20: =F19-E20 | G20: =ROUND(($B$3+$E$5)/$E$3,2) | H20: =H19-G20 | I20: =B20-B19 | J20: =B20-B19
A21: 12 | B21: =EOMONTH($E$5,12) | C21: =IF(12=$B$5,F20+D21,$H$4) | D21: =ROUND(F20*$B$4/100*J21/365,2) | E21: =C21-D21 | F21: =F20-E21 | G21: =ROUND(($B$3+$E$5)/$E$3,2) | H21: =H20-G21 | I21: =B21-B20 | J21: =B21-B20
A22: 13 | B22: =EOMONTH($E$5,13) | C22: =IF(13=$B$5,F21+D22,$H$4) | D22: =ROUND(F21*$B$4/100*J22/365,2) | E22: =C22-D22 | F22: =F21-E22 | G22: =ROUND(($B$3+$E$5)/$E$3,2) | H22: =H21-G22 | I22: =B22-B21 | J22: =B22-B21
A23: 14 | B23: =EOMONTH($E$5,14) | C23: =IF(14=$B$5,F22+D23,$H$4) | D23: =ROUND(F22*$B$4/100*J23/365,2) | E23: =C23-D23 | F23: =F22-E23 | G23: =ROUND(($B$3+$E$5)/$E$3,2) | H23: =H22-G23 | I23: =B23-B22 | J23: =B23-B22
A24: 15 | B24: =EOMONTH($E$5,15) | C24: =IF(15=$B$5,F23+D24,$H$4) | D24: =ROUND(F23*$B$4/100*J24/365,2) | E24: =C24-D24 | F24: =F23-E24 | G24: =ROUND(($B$3+$E$5)/$E$3,2) | H24: =H23-G24 | I24: =B24-B23 | J24: =B24-B23
A25: 16 | B25: =EOMONTH($E$5,16) | C25: =IF(16=$B$5,F24+D25,$H$4) | D25: =ROUND(F24*$B$4/100*J25/365,2) | E25: =C25-D25 | F25: =F24-E25 | G25: =ROUND(($B$3+$E$5)/$E$3,2) | H25: =H24-G25 | I25: =B25-B24 | J25: =B25-B24
A26: 17 | B26: =EOMONTH($E$5,17) | C26: =IF(17=$B$5,F25+D26,$H$4) | D26: =ROUND(F25*$B$4/100*J26/365,2) | E26: =C26-D26 | F26: =F25-E26 | G26: =ROUND(($B$3+$E$5)/$E$3,2) | H26: =H25-G26 | I26: =B26-B25 | J26: =B26-B25
A27: 18 | B27: =EOMONTH($E$5,18) | C27: =IF(18=$B$5,F26+D27,$H$4) | D27: =ROUND(F26*$B$4/100*J27/365,2) | E27: =C27-D27 | F27: =F26-E27 | G27: =ROUND(($B$3+$E$5)/$E$3,2) | H27: =H26-G27 | I27: =B27-B26 | J27: =B27-B26
A28: 19 | B28: =EOMONTH($E$5,19) | C28: =IF(19=$B$5,F27+D28,$H$4) | D28: =ROUND(F27*$B$4/100*J28/365,2) | E28: =C28-D28 | F28: =F27-E28 | G28: =ROUND(($B$3+$E$5)/$E$3,2) | H28: =H27-G28 | I28: =B28-B27 | J28: =B28-B27
A29: 20 | B29: =EOMONTH($E$5,20) | C29: =IF(20=$B$5,F28+D29,$H$4) | D29: =ROUND(F28*$B$4/100*J29/365,2) | E29: =C29-D29 | F29: =F28-E29 | G29: =ROUND(($B$3+$E$5)/$E$3,2) | H29: =H28-G29 | I29: =B29-B28 | J29: =B29-B28
A30: 21 | B30: =EOMONTH($E$5,21) | C30: =IF(21=$B$5,F29+D30,$H$4) | D30: =ROUND(F29*$B$4/100*J30/365,2) | E30: =C30-D30 | F30: =F29-E30 | G30: =ROUND(($B$3+$E$5)/$E$3,2) | H30: =H29-G30 | I30: =B30-B29 | J30: =B30-B29
A31: 22 | B31: =EOMONTH($E$5,22) | C31: =IF(22=$B$5,F30+D31,$H$4) | D31: =ROUND(F30*$B$4/100*J31/365,2) | E31: =C31-D31 | F31: =F30-E31 | G31: =ROUND(($B$3+$E$5)/$E$3,2) | H31: =H30-G31 | I31: =B31-B30 | J31: =B31-B30
A32: 23 | B32: =EOMONTH($E$5,23) | C32: =IF(23=$B$5,F31+D32,$H$4) | D32: =ROUND(F31*$B$4/100*J32/365,2) | E32: =C32-D32 | F32: =F31-E32 | G32: =ROUND(($B$3+$E$5)/$E$3,2) | H32: =H31-G32 | I32: =B32-B31 | J32: =B32-B31
A33: 24 | B33: =EOMONTH($E$5,24) | C33: =IF(24=$B$5,F32+D33,$H$4) | D33: =ROUND(F32*$B$4/100*J33/365,2) | E33: =C33-D33 | F33: =F32-E33 | G33: =ROUND(($B$3+$E$5)/$E$3,2) | H33: =H32-G33 | I33: =B33-B32 | J33: =B33-B32
A34: 25 | B34: =EOMONTH($E$5,25) | C34: =IF(25=$B$5,F33+D34,$H$4) | D34: =ROUND(F33*$B$4/100*J34/365,2) | E34: =C34-D34 | F34: =F33-E34 | G34: =ROUND(($B$3+$E$5)/$E$3,2) | H34: =H33-G34 | I34: =B34-B33 | J34: =B34-B33
A35: 26 | B35: =EOMONTH($E$5,26) | C35: =IF(26=$B$5,F34+D35,$H$4) | D35: =ROUND(F34*$B$4/100*J35/365,2) | E35: =C35-D35 | F35: =F34-E35 | G35: =ROUND(($B$3+$E$5)/$E$3,2) | H35: =H34-G35 | I35: =B35-B34 | J35: =B35-B34
A36: 27 | B36: =EOMONTH($E$5,27) | C36: =IF(27=$B$5,F35+D36,$H$4) | D36: =ROUND(F35*$B$4/100*J36/365,2) | E36: =C36-D36 | F36: =F35-E36 | G36: =ROUND(($B$3+$E$5)/$E$3,2) | H36: =H35-G36 | I36: =B36-B35 | J36: =B36-B35
A37: 28 | B37: =EOMONTH($E$5,28) | C37: =IF(28=$B$5,F36+D37,$H$4) | D37: =ROUND(F36*$B$4/100*J37/365,2) | E37: =C37-D37 | F37: =F36-E37 | G37: =ROUND(($B$3+$E$5)/$E$3,2) | H37: =H36-G37 | I37: =B37-B36 | J37: =B37-B36
A38: 29 | B38: =EOMONTH($E$5,29) | C38: =IF(29=$B$5,F37+D38,$H$4) | D38: =ROUND(F37*$B$4/100*J38/365,2) | E38: =C38-D38 | F38: =F37-E38 | G38: =ROUND(($B$3+$E$5)/$E$3,2) | H38: =H37-G38 | I38: =B38-B37 | J38: =B38-B37
A39: 30 | B39: =EOMONTH($E$5,30) | C39: =IF(30=$B$5,F38+D39,$H$4) | D39: =ROUND(F38*$B$4/100*J39/365,2) | E39: =C39-D39 | F39: =F38-E39 | G39: =ROUND(($B$3+$E$5)/$E$3,2) | H39: =H38-G39 | I39: =B39-B38 | J39: =B39-B38
A40: 31 | B40: =EOMONTH($E$5,31) | C40: =IF(31=$B$5,F39+D40,$H$4) | D40: =ROUND(F39*$B$4/100*J40/365,2) | E40: =C40-D40 | F40: =F39-E40 | G40: =ROUND(($B$3+$E$5)/$E$3,2) | H40: =H39-G40 | I40: =B40-B39 | J40: =B40-B39
A41: 32 | B41: =EOMONTH($E$5,32) | C41: =IF(32=$B$5,F40+D41,$H$4) | D41: =ROUND(F40*$B$4/100*J41/365,2) | E41: =C41-D41 | F41: =F40-E41 | G41: =ROUND(($B$3+$E$5)/$E$3,2) | H41: =H40-G41 | I41: =B41-B40 | J41: =B41-B40
A42: 33 | B42: =EOMONTH($E$5,33) | C42: =IF(33=$B$5,F41+D42,$H$4) | D42: =ROUND(F41*$B$4/100*J42/365,2) | E42: =C42-D42 | F42: =F41-E42 | G42: =ROUND(($B$3+$E$5)/$E$3,2) | H42: =H41-G42 | I42: =B42-B41 | J42: =B42-B41
A43: 34 | B43: =EOMONTH($E$5,34) | C43: =IF(34=$B$5,F42+D43,$H$4) | D43: =ROUND(F42*$B$4/100*J43/365,2) | E43: =C43-D43 | F43: =F42-E43 | G43: =ROUND(($B$3+$E$5)/$E$3,2) | H43: =H42-G43 | I43: =B43-B42 | J43: =B43-B42
A44: 35 | B44: =EOMONTH($E$5,35) | C44: =IF(35=$B$5,F43+D44,$H$4) | D44: =ROUND(F43*$B$4/100*J44/365,2) | E44: =C44-D44 | F44: =F43-E44 | G44: =ROUND(($B$3+$E$5)/$E$3,2) | H44: =H43-G44 | I44: =B44-B43 | J44: =B44-B43
A45: 36 | B45: =EOMONTH($E$5,36) | C45: =IF(36=$B$5,F44+D45,$H$4) | D45: =ROUND(F44*$B$4/100*J45/365,2) | E45: =C45-D45 | F45: =F44-E45 | G45: =ROUND(($B$3+$E$5)/$E$3,2) | H45: =H44-G45 | I45: =B45-B44 | J45: =B45-B44
A46: 37 | B46: =EOMONTH($E$5,37) | C46: =IF(37=$B$5,F45+D46,$H$4) | D46: =ROUND(F45*$B$4/100*J46/365,2) | E46: =C46-D46 | F46: =F45-E46 | G46: =ROUND(($B$3+$E$5)/$E$3,2) | H46: =H45-G46 | I46: =B46-B45 | J46: =B46-B45
A47: 38 | B47: =EOMONTH($E$5,38) | C47: =IF(38=$B$5,F46+D47,$H$4) | D47: =ROUND(F46*$B$4/100*J47/365,2) | E47: =C47-D47 | F47: =F46-E47 | G47: =ROUND(($B$3+$E$5)/$E$3,2) | H47: =H46-G47 | I47: =B47-B46 | J47: =B47-B46
A48: 39 | B48: =EOMONTH($E$5,39) | C48: =IF(39=$B$5,F47+D48,$H$4) | D48: =ROUND(F47*$B$4/100*J48/365,2) | E48: =C48-D48 | F48: =F47-E48 | G48: =ROUND(($B$3+$E$5)/$E$3,2) | H48: =H47-G48 | I48: =B48-B47 | J48: =B48-B47
A49: 40 | B49: =EOMONTH($E$5,40) | C49: =IF(40=$B$5,F48+D49,$H$4) | D49: =ROUND(F48*$B$4/100*J49/365,2) | E49: =C49-D49 | F49: =F48-E49 | G49: =ROUND(($B$3+$E$5)/$E$3,2) | H49: =H48-G49 | I49: =B49-B48 | J49: =B49-B48
A50: 41 | B50: =EOMONTH($E$5,41) | C50: =IF(41=$B$5,F49+D50,$H$4) | D50: =ROUND(F49*$B$4/100*J50/365,2) | E50: =C50-D50 | F50: =F49-E50 | G50: =ROUND(($B$3+$E$5)/$E$3,2) | H50: =H49-G50 | I50: =B50-B49 | J50: =B50-B49
A51: 42 | B51: =EOMONTH($E$5,42) | C51: =IF(42=$B$5,F50+D51,$H$4) | D51: =ROUND(F50*$B$4/100*J51/365,2) | E51: =C51-D51 | F51: =F50-E51 | G51: =ROUND(($B$3+$E$5)/$E$3,2) | H51: =H50-G51 | I51: =B51-B50 | J51: =B51-B50
A52: 43 | B52: =EOMONTH($E$5,43) | C52: =IF(43=$B$5,F51+D52,$H$4) | D52: =ROUND(F51*$B$4/100*J52/365,2) | E52: =C52-D52 | F52: =F51-E52 | G52: =ROUND(($B$3+$E$5)/$E$3,2) | H52: =H51-G52 | I52: =B52-B51 | J52: =B52-B51
A53: 44 | B53: =EOMONTH($E$5,44) | C53: =IF(44=$B$5,F52+D53,$H$4) | D53: =ROUND(F52*$B$4/100*J53/365,2) | E53: =C53-D53 | F53: =F52-E53 | G53: =ROUND(($B$3+$E$5)/$E$3,2) | H53: =H52-G53 | I53: =B53-B52 | J53: =B53-B52
A54: 45 | B54: =EOMONTH($E$5,45) | C54: =IF(45=$B$5,F53+D54,$H$4) | D54: =ROUND(F53*$B$4/100*J54/365,2) | E54: =C54-D54 | F54: =F53-E54 | G54: =ROUND(($B$3+$E$5)/$E$3,2) | H54: =H53-G54 | I54: =B54-B53 | J54: =B54-B53
A55: 46 | B55: =EOMONTH($E$5,46) | C55: =IF(46=$B$5,F54+D55,$H$4) | D55: =ROUND(F54*$B$4/100*J55/365,2) | E55: =C55-D55 | F55: =F54-E55 | G55: =ROUND(($B$3+$E$5)/$E$3,2) | H55: =H54-G55 | I55: =B55-B54 | J55: =B55-B54
A56: 47 | B56: =EOMONTH($E$5,47) | C56: =IF(47=$B$5,F55+D56,$H$4) | D56: =ROUND(F55*$B$4/100*J56/365,2) | E56: =C56-D56 | F56: =F55-E56 | G56: =ROUND(($B$3+$E$5)/$E$3,2) | H56: =H55-G56 | I56: =B56-B55 | J56: =B56-B55
A57: 48 | B57: =EOMONTH($E$5,48) | C57: =IF(48=$B$5,F56+D57,$H$4) | D57: =ROUND(F56*$B$4/100*J57/365,2) | E57: =C57-D57 | F57: =F56-E57 | G57: =ROUND(($B$3+$E$5)/$E$3,2) | H57: =H56-G57 | I57: =B57-B56 | J57: =B57-B56
A58: 49 | B58: =EOMONTH($E$5,49) | C58: =IF(49=$B$5,F57+D58,$H$4) | D58: =ROUND(F57*$B$4/100*J58/365,2) | E58: =C58-D58 | F58: =F57-E58 | G58: =ROUND(($B$3+$E$5)/$E$3,2) | H58: =H57-G58 | I58: =B58-B57 | J58: =B58-B57
A59: 50 | B59: =EOMONTH($E$5,50) | C59: =IF(50=$B$5,F58+D59,$H$4) | D59: =ROUND(F58*$B$4/100*J59/365,2) | E59: =C59-D59 | F59: =F58-E59 | G59: =ROUND(($B$3+$E$5)/$E$3,2) | H59: =H58-G59 | I59: =B59-B58 | J59: =B59-B58
A60: 51 | B60: =EOMONTH($E$5,51) | C60: =IF(51=$B$5,F59+D60,$H$4) | D60: =ROUND(F59*$B$4/100*J60/365,2) | E60: =C60-D60 | F60: =F59-E60 | G60: =ROUND(($B$3+$E$5)/$E$3,2) | H60: =H59-G60 | I60: =B60-B59 | J60: =B60-B59
A61: 52 | B61: =EOMONTH($E$5,52) | C61: =IF(52=$B$5,F60+D61,$H$4) | D61: =ROUND(F60*$B$4/100*J61/365,2) | E61: =C61-D61 | F61: =F60-E61 | G61: =ROUND(($B$3+$E$5)/$E$3,2) | H61: =H60-G61 | I61: =B61-B60 | J61: =B61-B60
A62: 53 | B62: =EOMONTH($E$5,53) | C62: =IF(53=$B$5,F61+D62,$H$4) | D62: =ROUND(F61*$B$4/100*J62/365,2) | E62: =C62-D62 | F62: =F61-E62 | G62: =ROUND(($B$3+$E$5)/$E$3,2) | H62: =H61-G62 | I62: =B62-B61 | J62: =B62-B61
A63: 54 | B63: =EOMONTH($E$5,54) | C63: =IF(54=$B$5,F62+D63,$H$4) | D63: =ROUND(F62*$B$4/100*J63/365,2) | E63: =C63-D63 | F63: =F62-E63 | G63: =ROUND(($B$3+$E$5)/$E$3,2) | H63: =H62-G63 | I63: =B63-B62 | J63: =B63-B62
A64: 55 | B64: =EOMONTH($E$5,55) | C64: =IF(55=$B$5,F63+D64,$H$4) | D64: =ROUND(F63*$B$4/100*J64/365,2) | E64: =C64-D64 | F64: =F63-E64 | G64: =ROUND(($B$3+$E$5)/$E$3,2) | H64: =H63-G64 | I64: =B64-B63 | J64: =B64-B63
A65: 56 | B65: =EOMONTH($E$5,56) | C65: =IF(56=$B$5,F64+D65,$H$4) | D65: =ROUND(F64*$B$4/100*J65/365,2) | E65: =C65-D65 | F65: =F64-E65 | G65: =ROUND(($B$3+$E$5)/$E$3,2) | H65: =H64-G65 | I65: =B65-B64 | J65: =B65-B64
A66: 57 | B66: =EOMONTH($E$5,57) | C66: =IF(57=$B$5,F65+D66,$H$4) | D66: =ROUND(F65*$B$4/100*J66/365,2) | E66: =C66-D66 | F66: =F65-E66 | G66: =ROUND(($B$3+$E$5)/$E$3,2) | H66: =H65-G66 | I66: =B66-B65 | J66: =B66-B65
A67: 58 | B67: =EOMONTH($E$5,58) | C67: =IF(58=$B$5,F66+D67,$H$4) | D67: =ROUND(F66*$B$4/100*J67/365,2) | E67: =C67-D67 | F67: =F66-E67 | G67: =ROUND(($B$3+$E$5)/$E$3,2) | H67: =H66-G67 | I67: =B67-B66 | J67: =B67-B66
A68: 59 | B68: =EOMONTH($E$5,59) | C68: =IF(59=$B$5,F67+D68,$H$4) | D68: =ROUND(F67*$B$4/100*J68/365,2) | E68: =C68-D68 | F68: =F67-E68 | G68: =ROUND(($B$3+$E$5)/$E$3,2) | H68: =H67-G68 | I68: =B68-B67 | J68: =B68-B67
A69: 60 | B69: =EOMONTH($E$5,60) | C69: =IF(60=$B$5,F68+D69,$H$4) | D69: =ROUND(F68*$B$4/100*J69/365,2) | E69: =C69-D69 | F69: =F68-E69 | G69: =ROUND(($B$3+$E$5)/$E$3,2) | H69: =H68-G69 | I69: =B69-B68 | J69: =B69-B68

Sheet Lease Other Maturity
A1: LSO-DEMO-001 — Maturity Profile
A3: GL Classification — Aging | D3: ที่มา / วิธีคิด (อ้างอิงแท็บ schedule)
A4: Current Portion (≤ 12 เดือน) | C4: =SUM('Lease Other'!E10:E21) | D4: รวม "เงินต้นตัดต่องวด" (คอลัมน์ PRINCIPAL (ตัดต้น) — ตัวเลขสีเขียว) ของงวดที่ 1–12
A5: Non-current (> 12 เดือน) | C5: =SUM('Lease Other'!E22:E69) | D5: รวม "เงินต้นตัดต่องวด" (PRINCIPAL สีเขียว) ของงวดที่ 13–60 (หรือ Total ลบ Current)
A6: Total Principal | C6: ='Lease Other'!$B$3 | D6: เงินต้นตั้งต้น — ช่อง PRINCIPAL / ROU (มุมบนซ้ายของแท็บ schedule)
A8: ภาระผูกพันในอนาคต (เงินต้น + ดอกเบี้ย ยังไม่คิดลด) | D8: ที่มา / วิธีคิด
A9: ภายใน 1 ปี | C9: =SUMPRODUCT(('Lease Other'!A10:A69<=12)*('Lease Other'!E10:E69+'Lease Other'!D10:D69)) | D9: รวม "เงินต้นตัดต่องวด (PRINCIPAL สีเขียว)" + "ดอกเบี้ย (INTEREST สีส้ม)" ของงวดที่ 1–12 (เงินสดที่จะจ่ายใน 1 ปีข้างหน้า)
A10: 1 - 5 ปี | C10: =SUMPRODUCT(('Lease Other'!A10:A69>12)*('Lease Other'!A10:A69<=60)*('Lease Other'!E10:E69+'Lease Other'!D10:D69)) | D10: รวม PRINCIPAL (สีเขียว) + INTEREST (สีส้ม) ของงวดที่ 13–60
A11: มากกว่า 5 ปี | C11: =SUMPRODUCT(('Lease Other'!A10:A69>60)*('Lease Other'!E10:E69+'Lease Other'!D10:D69)) | D11: รวม PRINCIPAL + INTEREST ของงวดที่เกิน 60 เดือน — สัญญามี 60 งวด จึงไม่มี = 0
A12: Total Future Cash Flow | C12: ='Lease Other'!$B$3+'Lease Other'!$H$5 | D12: ช่อง PRINCIPAL บวก "ดอกเบี้ยรวมทั้งสัญญา" (INTEREST สีส้มรวมทุกงวด) (กระแสเงินสดอนาคตทั้งหมด ยังไม่คิดลด)
A14: Lease Classification: Finance (net/ROU · TFRS16)
